metalabel/__init__.py
metalabel/app/__init__.py
metalabel/app/meta_api.py
metalabel/app/meta_detection.py
metalabel/app/meta_label.py
metalabel/app/meta_segment.py
metalabel/groundingdino/__init__.py
metalabel/groundingdino/version.py
metalabel/groundingdino/models/__init__.py
metalabel/groundingdino/models/registry.py
metalabel/groundingdino/models/GroundingDINO/__init__.py
metalabel/groundingdino/models/GroundingDINO/bertwarper.py
metalabel/groundingdino/models/GroundingDINO/fuse_modules.py
metalabel/groundingdino/models/GroundingDINO/groundingdino.py
metalabel/groundingdino/models/GroundingDINO/ms_deform_attn.py
metalabel/groundingdino/models/GroundingDINO/transformer.py
metalabel/groundingdino/models/GroundingDINO/transformer_vanilla.py
metalabel/groundingdino/models/GroundingDINO/utils.py
metalabel/groundingdino/models/GroundingDINO/backbone/__init__.py
metalabel/groundingdino/models/GroundingDINO/backbone/backbone.py
metalabel/groundingdino/models/GroundingDINO/backbone/position_encoding.py
metalabel/groundingdino/models/GroundingDINO/backbone/swin_transformer.py
metalabel/groundingdino/util/__init__.py
metalabel/groundingdino/util/box_ops.py
metalabel/groundingdino/util/get_tokenlizer.py
metalabel/groundingdino/util/inference.py
metalabel/groundingdino/util/logger.py
metalabel/groundingdino/util/misc.py
metalabel/groundingdino/util/slconfig.py
metalabel/groundingdino/util/slio.py
metalabel/groundingdino/util/time_counter.py
metalabel/groundingdino/util/utils.py
metalabel/groundingdino/util/visualizer.py
metalabel/groundingdino/util/vl_utils.py
metalabel/segment_anything/__init__.py
metalabel/segment_anything/automatic_mask_generator.py
metalabel/segment_anything/build_sam.py
metalabel/segment_anything/predictor.py
metalabel/segment_anything/modeling/__init__.py
metalabel/segment_anything/modeling/common.py
metalabel/segment_anything/modeling/image_encoder.py
metalabel/segment_anything/modeling/mask_decoder.py
meta_label-3.4.12.dist-info/METADATA
meta_label-3.4.12.dist-info/WHEEL
meta_label-3.4.12.dist-info/top_level.txt
meta_label-3.4.12.dist-info/zip-safe
meta_label-3.4.12.dist-info/RECORD
